Workbook
Name capex_power: Input_Output!$D$34
Name capex_subsurface: Input_Output!$D$16
Name coheat_feedin: Input_Output!$D$49
Name coheatloadhours: Input_Output!$D$41
Name cop: Input_Output!$D$20
Name Cprock: Input_Output!$K$7
Name Cpwater: Input_Output!$K$4
Name debt_share: Input_Output!$D$60
Name depreciation_time: Input_Output!$D$64
Name depth: Input_Output!$D$6
Name DistanceToGrid: Input_Output!$D$31
Name DrillCosts: Input_Output!$D$12
Name Efficiency: Input_Output!$K$12
Name efficiencydirectheat: Input_Output!$K$17
Name electricity_buy: Input_Output!$D$21
Name equity_return: Input_Output!$D$58
Name equity_share: Input_Output!$D$59
Name fiscal_benefit: Input_Output!$D$54
Name fiscal_stimulus: Input_Output!$D$51
Name fixedOMrate: Input_Output!$D$35
Name flowrate: Input_Output!$D$5
Name GridConVar: Input_Output!$D$33
Name GridInvest: Input_Output!$D$32
Name heat_capex: Input_Output!$D$43
Name heat_mwth: Input_Output!$D$40
Name heat_OMfixed: Input_Output!$D$45
Name heat_OMvar: Input_Output!$D$46
Name heat_power: Input_Output!$B$40
Name inflation: Input_Output!$D$56
Name lifetime: Input_Output!$D$9
Name loan_rate: Input_Output!$D$57
Name nrofwells: Input_Output!$D$15
Name ooperation_choice: Input_Output!$G$2
Name PlantInvest: Input_Output!$D$30
Name Power: Input_Output!$D$28
Name power_feedin: Input_Output!$D$48
Name power_loadhours: Input_Output!$D$29
Name power_OMfixed: Input_Output!$D$36
Name power_OMvar: Input_Output!$D$37
Name pumpcost2: Input_Output!$D$14
Name pumps: Input_Output!$D$15
Name Rhorock: Input_Output!$K$8
Name Rhowater: Input_Output!$K$5
Name StimCosts: Input_Output!$D$13
Name stimulus_max: Input_Output!$D$53
Name stimulus_perc: Input_Output!$D$52
Name tax: Input_Output!$D$61
Name Tbase: Input_Output!$K$14
Name term_loan: Input_Output!$D$63
Name thermalpower_power: Input_Output!$D$27
Name toutlet: Input_Output!$D$25
Name Treinject: Input_Output!$D$39
Name Ts: Input_Output!$D$7
Name Tx: Input_Output!$D$8
Name variable_OM_pumps: Input_Output!$D$22
Name well_pump: Input_Output!$B$14
Name wellcostscaling: Input_Output!$D$11

Sheet Colofon
C2: Calculation of LCOE of renewable heat and electricity
C3: Geothermal electricity and heat
B6: authors | C6: Jan-Diederik van Wees, Lars ten Kulve, Derk Straathof, Maarten Pluymaekers
B7: date | C7: 10-07-2011
B8: sources | C8: Cash flow methodology is largely based on dutch economic models and spreadsheets developed by Energie Centrum Nederland (ECN, www.ecn.nl)
B9: version | C9: 2012.1
B11: Contact | C11: Contact jan-diederik van Wees. Jan_diederik.vanwees@tno.nl, +31651338919
B12: color coding
B13: do not enter value (calculated by other cells)
B14: enter value
B15: field in relevant in the calculation

Sheet Input_Output
A1: =Colofon!C2 -> Calculation of LCOE of renewable heat and electricity
A2: =Colofon!C3 -> Geothermal electricity and heat | B2: Geothermal Energy | E2: Operational choice | G2: heat | J2: rock and fluid properties
J3: parameter | K3: Value | L3: Unit
B4: INPUTVARIABLES | C4: used | D4: Value | E4: Unit | F4: Comment | J4: Cpwater | K4: 4250 | L4: J/kg K
B5: Flowrate | C5: 1 | D5: 70 | E5: L/s | F5: total flow rate which is achieved from the subsurface (measured at surface conditions) | J5: 𝜌water | K5: 1078 | L5: kg/m3
B6: along hole depth of a single well | C6: 1 | D6: 1800 | E6: m | F6: along hole depth (total length) of a single borehole in the subsurface
B7: Surface temperature | C7: 1 | D7: 10 | E7: C | F7: average yearly surface temperature | J7: Cprock | K7: 1000 | L7: J/kg K
B8: production temperature (Tx) | C8: 1 | D8: =2.7*31+Ts -> 93.7 | E8: C | F8: production temperature (reservoir temperature, corrected for temperature losses) | J8: 𝜌rock | K8: 2700 | L8: kg/m3
B9: Economic lifetime | C9: 1 | D9: 15 | E9: Years | F9: lifetime for cash flow calculations
B10: subsurface | J10: power conversion
B11: well cost scaling factor | C11: 1 | D11: 1.5 | E11: ="-" -> - | F11: scaling factor for calculating well costs | J11: relative efficiency | K11: 0.6 | L11: ="-" -> -
B12: well costs | C12: 1 | D12: =wellcostscaling*(0.2*depth^2+700*depth+250000)*10^-6 -> 3.237 | E12: mln euro/Well | F12: calculated costs for drillling the wells | J12: total conversion efficiency | K12: =(Tx-Ts)/(Tx+Ts+2*273.15)*K11 -> 0.077261538 | L12: ="-" -> -
B13: Stimulation and other Cost | C13: 1 | D13: 0 | E13: mln euro/Well | F13: additional well costs for stimulation (and other costs) of the reservoir | J13: offset for Tbase | K13: 70 | L13: C
B14: Pump investment | C14: 1 | D14: 0.3 | E14: Mln euro/pump | F14: pump investements. Workover is assumed every 5 years at installment costs | J14: Tbase (minimum Tx for power) | K14: =IF(ooperation_choice="heat",Tx,MIN(Ts+K13,Tx)) -> 93.7 | L14: C
B15: Number of wells | C15: 1 | D15: 2 | E15: ="-" -> - | F15: number of wells in the reservoir
B16: subsurface capex | C16: 1 | D16: =(StimCosts+DrillCosts)*nrofwells+pumpcost2 -> 6.774 | E16: mln euro | F16: calculated subsurface capex for wells, stimulation and pumps | J16: heat (cold) conversion
B17: subsurface parasitic | J17: total efficiency | K17: 1 | L17: ="-" -> -
B18: pressure of water loop | D18: 0 | E18: bar
B19: electricity consumption | D19: =flowrate*0.001*D18*0.1/0.6 -> 0 | E19: MWe | J19: units
B20: COP | C20: 1 | D20: 27 | E20: ="-" -> - | F20: coefficient of performance (MWth/MWe) to drive the pumps. Ratio of thermal and electric power. | J20: Seconds per year | K20: =60*60*24*365.25 -> 31557600 | L20: s
B21: electricity price for driving the pumps | C21: 1 | D21: 150 | E21: euro /MWhe | F21: electricity price for the power consumed by the subsurface pumps | J21: seconds per 30 years | K21: =K20*30 -> 946728000 | L21: s
B22: Variable O&M | C22: 1 | D22: =D21/D20 -> 5.5555556 | E22: euro/MWhth | F22: calculated variable O&M per unit of heat produced (1MWhth=3.6GJ) | J22: Ultimate recovery
B23: power temperature range used | J23: subsurface area | K23: 4.5 | L23: km2
B24: (co) heat relative starting temperature | C24: =IF(ooperation_choice="power",0,1) -> 1 | D24: 0 | E24: % | F24: relative value (100%= Tx,0%=Tbase) for upper limit of temperature range for heat | J24: subsurface thickness | K24: 100 | L24: m
B25: outlet temperature power plant (Toutlet) | C25: =IF(ooperation_choice="heat",0,1) -> 0 | D25: =IF(ooperation_choice="power-coheat",Tbase+D24*(Tx-Tbase),Tbase) -> 93.7 | E25: C | F25: upper limit of Temperature for (co)heat use | J25: rock volume involved | K25: =K23*1000000*K24 -> 450000000 | L25: m3
B26: power surface facilities | J26: UR for volume | K26: =(flowrate*0.001*Rhowater*Cpwater)/(K25*Rhorock*Cprock*(1/K21)) -> 0.24989334
B27: thermal power for electricity | C27: =IF(ooperation_choice="heat",0,1) -> 0 | D27: =flowrate*Cpwater*Rhowater*(Tx-toutlet)*10^-9 -> 0 | E27: MWth | F27: net power produced, taking into account the relative efficiency recorded by operating binary and flash plants
B28: electric power | D28: =D27*Efficiency -> 0 | E28: MWe | F28: net power produced, taking into account the relative efficiency recorded by operating binary and flash plants
B29: power Loadtime | C29: =IF(ooperation_choice="heat",0,1) -> 0 | D29: 8000 | E29: hours/year | F29: effective load hours in a year for electricity production
B30: power Plant investment costs | C30: =IF(ooperation_choice="heat",0,1) -> 0 | D30: 3 | E30: ="mln Euro/" &E28 -> mln Euro/MWe | F30: costs for power conversion system
B31: power Distance to grid | C31: =IF(ooperation_choice="heat",0,1) -> 0 | D31: 5000 | E31: m | F31: distance for the connection to the power grid
B32: power Grid investment | C32: =IF(ooperation_choice="heat",0,1) -> 0 | D32: 80 | E32: Euro/kWe | F32: grid connection cost per unit of power installed
B33: power Grid Connection Variable | C33: =IF(ooperation_choice="heat",0,1) -> 0 | D33: 100 | E33: Euro/m | F33: grid connection cost per unit of distance
B34: power plant capex | C34: =IF(ooperation_choice="heat",0,1) -> 0 | D34: =IF(Power>0,Power*PlantInvest+GridInvest*Power*0.001+DistanceToGrid*GridConVar*0.000001,0) -> 0 | E34: mln Euro | F34: calculated capex for power plant and grid connection
B35: power Fixed O&M rate | C35: =IF(ooperation_choice="heat",0,1) -> 0 | D35: 0.01 | E35: % | F35: O&M costs as percentage of caclulated capex for (sub)surface facilities
B36: power Fixed O&M | C36: =IF(ooperation_choice="heat",0,1) -> 0 | D36: =fixedOMrate*(capex_power+capex_subsurface)*100 -> 6.774 | E36: ="kEuro/" &E28 -> kEuro/MWe | F36: calculated O&M costs per unit of power installed
B37: power Variable O&M | C37: =IF(ooperation_choice="heat",0,1) -> 0 | D37: =D22/Efficiency -> 71.905837 | E37: Euro/MWhe | F37: calculated variable O&M costs (dependent on COP, and efficiency of conversion)
B38: (co)heat surface facilities
B39: direct heat reinjection temperature(Treinject) | C39: =IF(ooperation_choice="power",0,1) -> 1 | D39: 30 | E39: C | F39: reinjection temperature (effective temperature range is Toutlet..Treinject)
B40: direct heat production | C40: =IF(ooperation_choice="power",0,1) -> 1 | D40: =IF(ooperation_choice="power",0,efficiencydirectheat*flowrate*Cpwater*Rhowater*(toutlet-Treinject)*10^-9) -> 20.428909 | E40: MWth | F40: heat production
B41: direct heat load hours | C41: =IF(ooperation_choice="power",0,1) -> 1 | D41: 6000 | E41: hours/year | F41: effective load hours in a year for heat production
B42: direct heat plant investment costs | C42: =IF(ooperation_choice="power",0,1) -> 1 | D42: 150 | E42: kEuro/MWth | F42: heat surface installation costs per unit of heat production
B43: direct heat capex | C43: =IF(ooperation_choice="power",0,1) -> 1 | D43: =D42*D40/1000 -> 3.0643363 | E43: mln Euro | F43: calculate capex for heat production surface facilities
B44: direct heat Fixed O&M rate | C44: =IF(ooperation_choice="power",0,1) -> 1 | D44: 0.01 | E44: % | F44: O&M costs as percentage of caclulated capex for (sub) surface facilities
B45: direct heat Fixed O&M | C45: =IF(ooperation_choice="power",0,1) -> 1 | D45: =D44*(heat_capex+capex_subsurface)*100 -> 9.8383363 | E45: kEuro/MWth | F45: calculated O&M costs per unit of heat production installed
B46: direct heat Variable O&M | C46: =IF(ooperation_choice="heat",1,0) -> 1 | D46: =D22 -> 5.5555556 | E46: Eur/MWHth | F46: calculated variable O&M costs (dependent on COP)
B47: complementary sales
B48: complementary electricity sales | C48: =1 -> 1 | D48: 0 | E48: Euro/MWh | F48: complementary revenues from electricity sales
B49: complementary heat sales | C49: =1 -> 1 | D49: 0 | E49: euro/GJ | F49: complementary revennues from heat sales
B50: fiscal stimulus
B51: fiscal stimulus on lowering EBT | C51: 1 | D51: no | E51: yes/no | F51: apply fiscal stimulus on lowering earnings before tax (EBT) of the project developer
B52: percentage of CAPEX for fiscal stimulus | C52: 1 | D52: 0 | E52: % | F52: percentage of CAPEX which can be deducted from EBT
B53: legal max in allowed tax deduction | C53: 1 | D53: =D52*151 -> 0 | E53: mln Euro | F53: legal maximum in tax benefit
B54: NPV of benefit to project | C54: 1 | D54: =CFpower!C34/1000000 -> 0 | E54: mln Euro | F54: effective benefit to project
B56: Inflation | C56: 1 | D56: 0 | E56: % | F56: inflation for costs and benefits in project cash flow
B57: loan rate | C57: 1 | D57: 0.06 | E57: % | F57: interest rate on debt
B58: Required return on equity | C58: 1 | D58: 0.15 | E58: % | F58: required return on equity
B59: Equity share in investment | C59: 1 | D59: 0.2 | E59: % | F59: share of equity in the effective investment
B60: Debt share in investment | C60: 1 | D60: =1-D59 -> 0.8 | E60: % | F60: share of debt(the loan) in effective investment
B61: Tax | C61: 1 | D61: 0.25 | E61: % | F61: tax rate for company
B63: Term Loan | C63: 1 | D63: 15 | E63: Year | F63: number of years for the loan
B64: Depreciation period | C64: 1 | D64: 15 | E64: Year | F64: number of years for depreciation (linear per unit of production)
B66: POWER (power,co-heat) | C66: used | D66: Value | E66: Unit
B67: levelized cost of energy (LCOE) | C67: =IF(ooperation_choice="heat",0,1) -> 0 | D67: =IF(ooperation_choice="heat",0,100*(CFpower!C36-CFpower!D27)/CFpower!D28/100) -> 0 | E67: Euro/Mwhe
B69: HEAT SHEET (heat) | D69: Value | E69: Unit
B70: levelized cost of energy (LCOE) | C70: =IF(ooperation_choice="heat",1,0) -> 1 | D70: =IF(ooperation_choice="heat",100*(CFheat!C36-CFheat!D27)/CFheat!D28/100, 0) -> 4.7997816 | E70: Euro/GJ
E71: 1MWhth=3.6GJ
B75: GEOTWIN-DC — HYBRID SYSTEM ADDITIONS | Data Drillers · SPE Africa Geothermal Datathon 2026
B76: Blue = user input | Black = formula | Yellow = key assumption | Green = result
B77: Parameter | D77: Scenario A (Geo Only) | E77: Scenario B (Geo + HP) | F77: Scenario C ★ (Geo+HP+Storage) | G77: Scenario D (Geo+HP+Stor+Solar) | H77: Unit | I77: Notes
B78: ── CAPEX
B79: Subsurface CAPEX | D79: 7.074 | E79: 7.074 | F79: 7.074 | G79: 7.074 | H79: mln € | I79: n_wells×(drill+stim)+pumps
B80: Surface Infrastructure | D80: =Input_Output!$D$43 -> 3.0643363 | E80: =Input_Output!$D$43 -> 3.0643363 | F80: =Input_Output!$D$43 -> 3.0643363 | G80: =Input_Output!$D$43 -> 3.0643363 | H80: mln € | I80: heat_capex from template
B81: Heat Pump CAPEX | D81: 0 | E81: 6 | F81: 3.75 | G81: 3.75 | H81: mln € | I81: Scen B/C/D
B82: Thermal Storage CAPEX | D82: 0 | E82: 0 | F82: 12 | G82: 12 | H82: mln € | I82: 120 MWh × €0.1M/MWh
B83: Solar/Waste Heat CAPEX | D83: 0 | E83: 0 | F83: 0 | G83: 2.5 | H83: mln € | I83: Scenario D only
B84: TOTAL CAPEX | D84: =D79+D80+D81+D82+D83 -> 10.138336 | E84: =E79+E80+E81+E82+E83 -> 16.138336 | F84: =F79+F80+F81+F82+F83 -> 25.888336 | G84: =G79+G80+G81+G82+G83 -> 28.388336 | H84: mln € | I84: Sum of all items
B85: ── OPEX
B86: Fixed O&M | D86: =Input_Output!$D$45 -> 9.8383363 | E86: =Input_Output!$D$45 -> 9.8383363 | F86: =Input_Output!$D$45 -> 9.8383363 | G86: =Input_Output!$D$45 -> 9.8383363 | H86: kEuro/yr | I86: 1% of CAPEX, from template
B87: Variable O&M | D87: 5.556 | E87: 5.556 | F87: 5.556 | G87: 5.556 | H87: €/MWh | I87: template D46
B88: Pump Workover (Y5/10/15) | D88: 300000 | E88: 300000 | F88: 300000 | G88: 300000 | H88: € | I88: template D14×1000
B89: ── THERMAL ENERGY
B90: Geo Thermal Supply (template) | D90: =Input_Output!$D$40 -> 20.428909 | E90: =Input_Output!$D$40 -> 20.428909 | F90: =Input_Output!$D$40 -> 20.428909 | G90: =Input_Output!$D$40 -> 20.428909 | H90: MWth | I90: flow×cp×rho×ΔT×1e-9
B91: Heat Pump Boost | D91: 0 | E91: 4 | F91: 2.5 | G91: 2.5 | H91: MWth | I91: Scen B/C/D
B92: Solar/Waste Heat (avg) | D92: 0 | E92: 0 | F92: 0 | G92: 3 | H92: MWth | I92: Scenario D seasonal avg
B93: Total Installed Cap | D93: =IFERROR(D90+D91+D92,D90) -> 20.428909 | E93: =IFERROR(E90+E91+E92,E90) -> 24.428909 | F93: =IFERROR(F90+F91+F92,F90) -> 22.928909 | G93: =IFERROR(G90+G91+G92,G90) -> 25.928909 | H93: MWth | I93: Geo+HP+Solar
B94: Annual Heat (GJ/yr) | D94: =Input_Output!$D$40*Input_Output!$D$41*3.6 -> 441264.42 | E94: =Input_Output!$D$40*Input_Output!$D$41*3.6 -> 441264.42 | F94: =Input_Output!$D$40*Input_Output!$D$41*3.6 -> 441264.42 | G94: =Input_Output!$D$40*Input_Output!$D$41*3.6 -> 441264.42 | H94: GJ/yr | I94: geo×6000×3.6
B95: ── FINANCIAL
B96: WACC | D96: 0.066 | E96: 0.066 | F96: 0.066 | G96: 0.066 | H96: % | I96: 6.6% verified
B97: Reliability (%) | D97: 97.76 | E97: 100 | F97: 100 | G97: 100 | H97: % | I97: from Python simulation, avg_demand=15 MW
B98: ── LCoE RESULTS
B99: LCoE (€/GJ) — CFheat template | D99: 3.9216 | E99: 4.8174 | F99: 7.5102 | G99: 8.034 | H99: €/GJ | I99: from CFheat!D70 per scenario run
B100: LCoE (€/MWh) — GEOTWIN-DC | D100: =D99*3.6 -> 14.11776 | E100: =E99*3.6 -> 17.34264 | F100: =F99*3.6 -> 27.03672 | G100: =G99*3.6 -> 28.9224 | H100: €/MWh | I100: ×3.6 conversion
B101: CO₂ Offset (lifetime tonnes) | D101: 525575 | E101: 577973 | F101: 563834 | G101: 559577 | H101: t CO₂ | I101: annual_mwh×0.24×15
B102: ── SCENARIO DECISION
B103: Project Status | D103: REJECTED ✗ | E103: REVIEW ⚠ | F103: OPTIMAL ✓ | G103: REJECTED ✗ | I103: See notes
B104: Recommended Action | D104: Reliability OK but no cooling support | E104: Borderline — monitor peak demand buffer | F104: Proceed — best LCoE + full reliability | G104: Over-capitalised vs Scenario C

Sheet CFpower
A1: =Colofon!C2 -> Calculation of LCOE of renewable heat and electricity
A2: Geothermal power (and co-heat)
C4: Year | E4: 0 | F4: 1 | G4: 2 | H4: 3 | I4: 4 | J4: 5 | K4: 6 | L4: 7 | M4: 8 | N4: 9 | O4: 10 | P4: 11 | Q4: 12 | R4: 13 | S4: 14 | T4: 15 | U4: 16 | V4: 17 | W4: 18 | X4: 19 | Y4: 20 | Z4: 21 | AA4: 22 | AB4: 23 | AC4: 24 | AD4: 25 | AE4: 26 | AF4: 27 | AG4: 28 | AH4: 29 | AI4: 30 | AJ4: 31 | AK4: 32 | AL4: 33 | AM4: 34 | AN4: 35 | AO4: 36 | AP4: 37 | AQ4: 38 | AR4: 39 | AS4: 40
B5: Investment | C5: Euro | E5: =-C30 -> -9838336.3
B8: Electricity(A) | C8: kWh | F8: =IF(F4>lifetime,0,Power*power_loadhours*1000) -> 0 | G8: =IF(G4>lifetime,0,Power*power_loadhours*1000) -> 0 | H8: =IF(H4>lifetime,0,Power*power_loadhours*1000) -> 0 | I8: =IF(I4>lifetime,0,Power*power_loadhours*1000) -> 0 | J8: =IF(J4>lifetime,0,Power*power_loadhours*1000) -> 0 | K8: =IF(K4>lifetime,0,Power*power_loadhours*1000) -> 0 | L8: =IF(L4>lifetime,0,Power*power_loadhours*1000) -> 0 | M8: =IF(M4>lifetime,0,Power*power_loadhours*1000) -> 0 | ... AS8: =IF(AS4>lifetime,0,Power*power_loadhours*1000) -> 0
B9: Operational Costs(B) | C9: Euro | F9: =IF(F4>lifetime,0,-(power_OMfixed*Power*1000+F8*0.001*power_OMvar+heat_mwth*(coheatloadhours*heat_OMvar+heat_OMfixed*1000))) -> -881950.09 | G9: =IF(G4>lifetime,0,-(power_OMfixed*Power*1000+G8*0.001*power_OMvar+heat_mwth*(coheatloadhours*heat_OMvar+heat_OMfixed*1000))) -> -881950.09 | H9: =IF(H4>lifetime,0,-(power_OMfixed*Power*1000+H8*0.001*power_OMvar+heat_mwth*(coheatloadhours*heat_OMvar+heat_OMfixed*1000))) -> -881950.09 | I9: =IF(I4>lifetime,0,-(power_OMfixed*Power*1000+I8*0.001*power_OMvar+heat_mwth*(coheatloadhours*heat_OMvar+heat_OMfixed*1000))) -> -881950.09 | J9: =IF(J4>lifetime,0,-(power_OMfixed*Power*1000+J8*0.001*power_OMvar+heat_mwth*(coheatloadhours*heat_OMvar+heat_OMfixed*1000))) -> -881950.09 | K9: =IF(K4>lifetime,0,-(power_OMfixed*Power*1000+K8*0.001*power_OMvar+heat_mwth*(coheatloadhours*heat_OMvar+heat_OMfixed*1000))) -> -881950.09 | L9: =IF(L4>lifetime,0,-(power_OMfixed*Power*1000+L8*0.001*power_OMvar+heat_mwth*(coheatloadhours*heat_OMvar+heat_OMfixed*1000))) -> -881950.09 | M9: =IF(M4>lifetime,0,-(power_OMfixed*Power*1000+M8*0.001*power_OMvar+heat_mwth*(coheatloadhours*heat_OMvar+heat_OMfixed*1000))) -> -881950.09 | ... AS9: =IF(AS4>lifetime,0,-(power_OMfixed*Power*1000+AS8*0.001*power_OMvar+heat_mwth*(coheatloadhours*heat_OMvar+heat_OMfixed*1000))) -> 0
B10: Installation Pump (C ) | C10: Euro | J10: =-pumpcost2*1000000 -> -300000 | O10: =-pumpcost2*1000000 -> -300000 | T10: =-pumpcost2*1000000 -> -300000 | Y10: =-pumpcost2*1000000 -> -300000 | AD10: =-pumpcost2*1000000 -> -300000 | AI10: =-pumpcost2*1000000 -> -300000 | AN10: =-pumpcost2*1000000 -> -300000 | AS10: =-pumpcost2*1000000 -> -300000
B11: Market value electricity&heat (D) | C11: Euro | F11: =F8*power_feedin*0.001+heat_mwth*coheatloadhours*coheat_feedin*3.6 -> 0 | G11: =G8*power_feedin*0.001+heat_mwth*coheatloadhours*coheat_feedin*3.6 -> 0 | H11: =H8*power_feedin*0.001+heat_mwth*coheatloadhours*coheat_feedin*3.6 -> 0 | I11: =I8*power_feedin*0.001+heat_mwth*coheatloadhours*coheat_feedin*3.6 -> 0 | J11: =J8*power_feedin*0.001+heat_mwth*coheatloadhours*coheat_feedin*3.6 -> 0 | K11: =K8*power_feedin*0.001+heat_mwth*coheatloadhours*coheat_feedin*3.6 -> 0 | L11: =L8*power_feedin*0.001+heat_mwth*coheatloadhours*coheat_feedin*3.6 -> 0 | M11: =M8*power_feedin*0.001+heat_mwth*coheatloadhours*coheat_feedin*3.6 -> 0 | ... AS11: =AS8*power_feedin*0.001+heat_mwth*coheatloadhours*coheat_feedin*3.6 -> 0
B13: Total income (E=D) | C13: Euro | F13: =IF(F4>lifetime,0,POWER(1+inflation,F4-$F$4)*SUM(F11:F11)) -> 0 | G13: =IF(G4>lifetime,0,POWER(1+inflation,G4-$F$4)*SUM(G11:G11)) -> 0 | H13: =IF(H4>lifetime,0,POWER(1+inflation,H4-$F$4)*SUM(H11:H11)) -> 0 | I13: =IF(I4>lifetime,0,POWER(1+inflation,I4-$F$4)*SUM(I11:I11)) -> 0 | J13: =IF(J4>lifetime,0,POWER(1+inflation,J4-$F$4)*SUM(J11:J11)) -> 0 | K13: =IF(K4>lifetime,0,POWER(1+inflation,K4-$F$4)*SUM(K11:K11)) -> 0 | L13: =IF(L4>lifetime,0,POWER(1+inflation,L4-$F$4)*SUM(L11:L11)) -> 0 | M13: =IF(M4>lifetime,0,POWER(1+inflation,M4-$F$4)*SUM(M11:M11)) -> 0 | ... AS13: =IF(AS4>lifetime,0,POWER(1+inflation,AS4-$F$4)*SUM(AS11:AS11)) -> 0
B14: Total costs (F=B+C) | C14: Euro | F14: =IF(F4>lifetime,0,POWER(1+inflation,F4-$F$4)*SUM(F9:F10)) -> -881950.09 | G14: =IF(G4>lifetime,0,POWER(1+inflation,G4-$F$4)*SUM(G9:G10)) -> -881950.09 | H14: =IF(H4>lifetime,0,POWER(1+inflation,H4-$F$4)*SUM(H9:H10)) -> -881950.09 | I14: =IF(I4>lifetime,0,POWER(1+inflation,I4-$F$4)*SUM(I9:I10)) -> -881950.09 | J14: =IF(J4>lifetime,0,POWER(1+inflation,J4-$F$4)*SUM(J9:J10)) -> -1181950.1 | K14: =IF(K4>lifetime,0,POWER(1+inflation,K4-$F$4)*SUM(K9:K10)) -> -881950.09 | L14: =IF(L4>lifetime,0,POWER(1+inflation,L4-$F$4)*SUM(L9:L10)) -> -881950.09 | M14: =IF(M4>lifetime,0,POWER(1+inflation,M4-$F$4)*SUM(M9:M10)) -> -881950.09 | ... AS14: =IF(AS4>lifetime,0,POWER(1+inflation,AS4-$F$4)*SUM(AS9:AS10)) -> 0
B15: Gross revenue (G=E+F) | C15: Euro | F15: =SUM(F13:F14) -> -881950.09 | G15: =SUM(G13:G14) -> -881950.09 | H15: =SUM(H13:H14) -> -881950.09 | I15: =SUM(I13:I14) -> -881950.09 | J15: =SUM(J13:J14) -> -1181950.1 | K15: =SUM(K13:K14) -> -881950.09 | L15: =SUM(L13:L14) -> -881950.09 | M15: =SUM(M13:M14) -> -881950.09 | ... AS15: =SUM(AS13:AS14) -> 0
B17: Depreciation (H) | C17: Euro | F17: =IF(F4>depreciation_time,0,-CFpower!$C$30/depreciation_time) -> -655889.09 | G17: =IF(G4>depreciation_time,0,-CFpower!$C$30/depreciation_time) -> -655889.09 | H17: =IF(H4>depreciation_time,0,-CFpower!$C$30/depreciation_time) -> -655889.09 | I17: =IF(I4>depreciation_time,0,-CFpower!$C$30/depreciation_time) -> -655889.09 | J17: =IF(J4>depreciation_time,0,-CFpower!$C$30/depreciation_time) -> -655889.09 | K17: =IF(K4>depreciation_time,0,-CFpower!$C$30/depreciation_time) -> -655889.09 | L17: =IF(L4>depreciation_time,0,-CFpower!$C$30/depreciation_time) -> -655889.09 | M17: =IF(M4>depreciation_time,0,-CFpower!$C$30/depreciation_time) -> -655889.09 | ... AS17: =IF(AS4>depreciation_time,0,-CFpower!$C$30/depreciation_time) -> 0
B18: interest (I) | C18: Euro | F18: =IF(F4>term_loan,0,IPMT(Input_Output!$D$57,F4,term_loan,CFpower!$C$35)) -> -472240.14 | G18: =IF(G4>term_loan,0,IPMT(Input_Output!$D$57,G4,term_loan,CFpower!$C$35)) -> -451951.4 | H18: =IF(H4>term_loan,0,IPMT(Input_Output!$D$57,H4,term_loan,CFpower!$C$35)) -> -430445.33 | I18: =IF(I4>term_loan,0,IPMT(Input_Output!$D$57,I4,term_loan,CFpower!$C$35)) -> -407648.9 | J18: =IF(J4>term_loan,0,IPMT(Input_Output!$D$57,J4,term_loan,CFpower!$C$35)) -> -383484.69 | K18: =IF(K4>term_loan,0,IPMT(Input_Output!$D$57,K4,term_loan,CFpower!$C$35)) -> -357870.62 | L18: =IF(L4>term_loan,0,IPMT(Input_Output!$D$57,L4,term_loan,CFpower!$C$35)) -> -330719.7 | M18: =IF(M4>term_loan,0,IPMT(Input_Output!$D$57,M4,term_loan,CFpower!$C$35)) -> -301939.74 | ... AS18: =IF(AS4>term_loan,0,IPMT(Input_Output!$D$57,AS4,term_loan,CFpower!$C$35)) -> 0
B19: payment (J) | C19: Euro | F19: =IF(F4>term_loan,0,PPMT(Input_Output!$D$57,F4,term_loan,CFpower!$C$35)) -> -338145.7 | G19: =IF(G4>term_loan,0,PPMT(Input_Output!$D$57,G4,term_loan,CFpower!$C$35)) -> -358434.44 | H19: =IF(H4>term_loan,0,PPMT(Input_Output!$D$57,H4,term_loan,CFpower!$C$35)) -> -379940.5 | I19: =IF(I4>term_loan,0,PPMT(Input_Output!$D$57,I4,term_loan,CFpower!$C$35)) -> -402736.93 | J19: =IF(J4>term_loan,0,PPMT(Input_Output!$D$57,J4,term_loan,CFpower!$C$35)) -> -426901.15 | K19: =IF(K4>term_loan,0,PPMT(Input_Output!$D$57,K4,term_loan,CFpower!$C$35)) -> -452515.22 | L19: =IF(L4>term_loan,0,PPMT(Input_Output!$D$57,L4,term_loan,CFpower!$C$35)) -> -479666.13 | M19: =IF(M4>term_loan,0,PPMT(Input_Output!$D$57,M4,term_loan,CFpower!$C$35)) -> -508446.1 | ... AS19: =IF(AS4>term_loan,0,PPMT(Input_Output!$D$57,AS4,term_loan,CFpower!$C$35)) -> 0
B20: Total loan charges (K=I+J) | C20: Euro | F20: =SUM(F18,F19) -> -810385.84 | G20: =SUM(G18,G19) -> -810385.84 | H20: =SUM(H18,H19) -> -810385.84 | I20: =SUM(I18,I19) -> -810385.84 | J20: =SUM(J18,J19) -> -810385.84 | K20: =SUM(K18,K19) -> -810385.84 | L20: =SUM(L18,L19) -> -810385.84 | M20: =SUM(M18,M19) -> -810385.84 | ... AS20: =SUM(AS18,AS19) -> 0
B22: Taxable income (L=G+D+I),needs to be recovered from sales | C22: Euro | F22: =F15+F17+F18 -> -2010079.3 | G22: =G15+G17+G18 -> -1989790.6 | H22: =H15+H17+H18 -> -1968284.5 | I22: =I15+I17+I18 -> -1945488.1 | J22: =J15+J17+J18 -> -2221323.9 | K22: =K15+K17+K18 -> -1895709.8 | L22: =L15+L17+L18 -> -1868558.9 | M22: =M15+M17+M18 -> -1839778.9 | ... AS22: =AS15+AS17+AS18 -> 0
B23: Tax (M) | C23: Euro | F23: =-tax*F22 -> 502519.83 | G23: =-tax*G22 -> 497447.64 | H23: =-tax*H22 -> 492071.13 | I23: =-tax*I22 -> 486372.02 | J23: =-tax*J22 -> 555330.97 | K23: =-tax*K22 -> 473927.45 | L23: =-tax*L22 -> 467139.72 | M23: =-tax*M22 -> 459944.73 | ... AS23: =-tax*AS22 -> 0
B25: Net revenue after taxes (N=G+K+M) | C25: Euro | F25: =F15+F20+F23 -> -1189816.1 | G25: =G15+G20+G23 -> -1194888.3 | H25: =H15+H20+H23 -> -1200264.8 | I25: =I15+I20+I23 -> -1205963.9 | J25: =J15+J20+J23 -> -1437005 | K25: =K15+K20+K23 -> -1218408.5 | L25: =L15+L20+L23 -> -1225196.2 | M25: =M15+M20+M23 -> -1232391.2 | ... AS25: =AS15+AS20+AS23 -> 0
B27: Discounted revenue | C27: euro | D27: =NPV(Input_Output!$D$58,F25:AS25) -> -7320761.2
B28: Discounted energy sales | C28: MWh | D28: =NPV(Input_Output!$D$58,F28:AS28) -> 0 | F28: =(1-tax)*F8*0.001 -> 0 | G28: =(1-tax)*G8*0.001 -> 0 | H28: =(1-tax)*H8*0.001 -> 0 | I28: =(1-tax)*I8*0.001 -> 0 | J28: =(1-tax)*J8*0.001 -> 0 | K28: =(1-tax)*K8*0.001 -> 0 | L28: =(1-tax)*L8*0.001 -> 0 | M28: =(1-tax)*M8*0.001 -> 0 | ... AS28: =(1-tax)*AS8*0.001 -> 0
B30: Total investment | C30: =(capex_subsurface+capex_power+heat_capex)*1000000 -> 9838336.3 | D30: Euro
B31: Project rate | C31: =(1-tax)*loan_rate*debt_share+equity_share*equity_return -> 0.066
B32: capex for fiscal stimulus | C32: =C30 -> 9838336.3 | D32: Euro
B33: fiscal lowering of Earnings before tax (EBT) | C33: =IF(fiscal_stimulus="yes",IF(stimulus_perc*C32>stimulus_max*1000000,stimulus_max*1000000,stimulus_perc*C32),0) -> 0 | D33: Euro
B34: NPV benefit to project | C34: =(C33*tax)/(1+CFpower!C31) -> 0 | D34: Euro
B35: Loan share | C35: =C30*debt_share-C34 -> 7870669 | D35: Euro
B36: Equity share | C36: =equity_share*C30 -> 1967667.3 | D36: Euro

Sheet CFheat
A1: =Colofon!C2 -> Calculation of LCOE of renewable heat and electricity
A2: geothermal heat
B4: Positive values = good for producer | C4: Year | E4: 0 | F4: 1 | G4: 2 | H4: 3 | I4: 4 | J4: 5 | K4: 6 | L4: 7 | M4: 8 | N4: 9 | O4: 10 | P4: 11 | Q4: 12 | R4: 13 | S4: 14 | T4: 15 | U4: 16 | V4: 17 | W4: 18 | X4: 19 | Y4: 20 | Z4: 21 | AA4: 22 | AB4: 23 | AC4: 24 | AD4: 25 | AE4: 26 | AF4: 27 | AG4: 28 | AH4: 29 | AI4: 30 | AJ4: 31 | AK4: 32 | AL4: 33 | AM4: 34 | AN4: 35 | AO4: 36 | AP4: 37 | AQ4: 38 | AR4: 39 | AS4: 40
B5: Investment | C5: Euro | E5: =-C30 -> -9838336.3
B8: heat(A) | C8: GJ | F8: =IF(F4>lifetime,0,heat_mwth*coheatloadhours*3.6) -> 441264.42 | G8: =IF(G4>lifetime,0,heat_mwth*coheatloadhours*3.6) -> 441264.42 | H8: =IF(H4>lifetime,0,heat_mwth*coheatloadhours*3.6) -> 441264.42 | I8: =IF(I4>lifetime,0,heat_mwth*coheatloadhours*3.6) -> 441264.42 | J8: =IF(J4>lifetime,0,heat_mwth*coheatloadhours*3.6) -> 441264.42 | K8: =IF(K4>lifetime,0,heat_mwth*coheatloadhours*3.6) -> 441264.42 | L8: =IF(L4>lifetime,0,heat_mwth*coheatloadhours*3.6) -> 441264.42 | M8: =IF(M4>lifetime,0,heat_mwth*coheatloadhours*3.6) -> 441264.42 | ... AS8: =IF(AS4>lifetime,0,heat_mwth*coheatloadhours*3.6) -> 0
B9: Operational Costs(B) | C9: Euro | F9: =IF(F4>lifetime,0,-(power_OMfixed*Power*1000+heat_mwth*(coheatloadhours*heat_OMvar+heat_OMfixed*1000))) -> -881950.09 | G9: =IF(G4>lifetime,0,-(power_OMfixed*Power*1000+heat_mwth*(coheatloadhours*heat_OMvar+heat_OMfixed*1000))) -> -881950.09 | H9: =IF(H4>lifetime,0,-(power_OMfixed*Power*1000+heat_mwth*(coheatloadhours*heat_OMvar+heat_OMfixed*1000))) -> -881950.09 | I9: =IF(I4>lifetime,0,-(power_OMfixed*Power*1000+heat_mwth*(coheatloadhours*heat_OMvar+heat_OMfixed*1000))) -> -881950.09 | J9: =IF(J4>lifetime,0,-(power_OMfixed*Power*1000+heat_mwth*(coheatloadhours*heat_OMvar+heat_OMfixed*1000))) -> -881950.09 | K9: =IF(K4>lifetime,0,-(power_OMfixed*Power*1000+heat_mwth*(coheatloadhours*heat_OMvar+heat_OMfixed*1000))) -> -881950.09 | L9: =IF(L4>lifetime,0,-(power_OMfixed*Power*1000+heat_mwth*(coheatloadhours*heat_OMvar+heat_OMfixed*1000))) -> -881950.09 | M9: =IF(M4>lifetime,0,-(power_OMfixed*Power*1000+heat_mwth*(coheatloadhours*heat_OMvar+heat_OMfixed*1000))) -> -881950.09 | ... AS9: =IF(AS4>lifetime,0,-(power_OMfixed*Power*1000+heat_mwth*(coheatloadhours*heat_OMvar+heat_OMfixed*1000))) -> 0
B10: Installation Pump (C ) | C10: Euro | J10: =-pumpcost2*1000000 -> -300000 | O10: =-pumpcost2*1000000 -> -300000 | T10: =-pumpcost2*1000000 -> -300000 | Y10: =-pumpcost2*pumps*1000000*0.5 -> -300000 | AD10: =-pumpcost2*1000000 -> -300000 | AI10: =-pumpcost2*1000000 -> -300000 | AN10: =-pumpcost2*1000000 -> -300000 | AS10: =-pumpcost2*1000000 -> -300000
B11: Market value electricity&heat (D) | C11: Euro | F11: =coheat_feedin*F8+Power*power_loadhours*power_feedin*3.6 -> 0 | G11: =coheat_feedin*G8+Power*power_loadhours*power_feedin*3.6 -> 0 | H11: =coheat_feedin*H8+Power*power_loadhours*power_feedin*3.6 -> 0 | I11: =coheat_feedin*I8+Power*power_loadhours*power_feedin*3.6 -> 0 | J11: =coheat_feedin*J8+Power*power_loadhours*power_feedin*3.6 -> 0 | K11: =coheat_feedin*K8+Power*power_loadhours*power_feedin*3.6 -> 0 | L11: =coheat_feedin*L8+Power*power_loadhours*power_feedin*3.6 -> 0 | M11: =coheat_feedin*M8+Power*power_loadhours*power_feedin*3.6 -> 0 | ... AS11: =coheat_feedin*AS8+Power*power_loadhours*power_feedin*3.6 -> 0
B13: Total income (E=D) | C13: Euro | F13: =IF(F4>lifetime,0,POWER(1+inflation,F4-$F$4)*SUM(F11:F11)) -> 0 | G13: =IF(G4>lifetime,0,POWER(1+inflation,G4-$F$4)*SUM(G11:G11)) -> 0 | H13: =IF(H4>lifetime,0,POWER(1+inflation,H4-$F$4)*SUM(H11:H11)) -> 0 | I13: =IF(I4>lifetime,0,POWER(1+inflation,I4-$F$4)*SUM(I11:I11)) -> 0 | J13: =IF(J4>lifetime,0,POWER(1+inflation,J4-$F$4)*SUM(J11:J11)) -> 0 | K13: =IF(K4>lifetime,0,POWER(1+inflation,K4-$F$4)*SUM(K11:K11)) -> 0 | L13: =IF(L4>lifetime,0,POWER(1+inflation,L4-$F$4)*SUM(L11:L11)) -> 0 | M13: =IF(M4>lifetime,0,POWER(1+inflation,M4-$F$4)*SUM(M11:M11)) -> 0 | ... AS13: =IF(AS4>lifetime,0,POWER(1+inflation,AS4-$F$4)*SUM(AS11:AS11)) -> 0
B14: Total costs (F=B+C) | C14: Euro | F14: =IF(F4>lifetime,0,POWER(1+inflation,F4-$F$4)*SUM(F9:F10)) -> -881950.09 | G14: =IF(G4>lifetime,0,POWER(1+inflation,G4-$F$4)*SUM(G9:G10)) -> -881950.09 | H14: =IF(H4>lifetime,0,POWER(1+inflation,H4-$F$4)*SUM(H9:H10)) -> -881950.09 | I14: =IF(I4>lifetime,0,POWER(1+inflation,I4-$F$4)*SUM(I9:I10)) -> -881950.09 | J14: =IF(J4>lifetime,0,POWER(1+inflation,J4-$F$4)*SUM(J9:J10)) -> -1181950.1 | K14: =IF(K4>lifetime,0,POWER(1+inflation,K4-$F$4)*SUM(K9:K10)) -> -881950.09 | L14: =IF(L4>lifetime,0,POWER(1+inflation,L4-$F$4)*SUM(L9:L10)) -> -881950.09 | M14: =IF(M4>lifetime,0,POWER(1+inflation,M4-$F$4)*SUM(M9:M10)) -> -881950.09 | ... AS14: =IF(AS4>lifetime,0,POWER(1+inflation,AS4-$F$4)*SUM(AS9:AS10)) -> 0
B15: Gross revenue (G=E+F) | C15: Euro | F15: =SUM(F13:F14) -> -881950.09 | G15: =SUM(G13:G14) -> -881950.09 | H15: =SUM(H13:H14) -> -881950.09 | I15: =SUM(I13:I14) -> -881950.09 | J15: =SUM(J13:J14) -> -1181950.1 | K15: =SUM(K13:K14) -> -881950.09 | L15: =SUM(L13:L14) -> -881950.09 | M15: =SUM(M13:M14) -> -881950.09 | ... AS15: =SUM(AS13:AS14) -> 0
B17: Depreciation (H) | C17: Euro | F17: =IF(F4>depreciation_time,0,-$C$30/depreciation_time) -> -655889.09 | G17: =IF(G4>depreciation_time,0,-$C$30/depreciation_time) -> -655889.09 | H17: =IF(H4>depreciation_time,0,-$C$30/depreciation_time) -> -655889.09 | I17: =IF(I4>depreciation_time,0,-$C$30/depreciation_time) -> -655889.09 | J17: =IF(J4>depreciation_time,0,-$C$30/depreciation_time) -> -655889.09 | K17: =IF(K4>depreciation_time,0,-$C$30/depreciation_time) -> -655889.09 | L17: =IF(L4>depreciation_time,0,-$C$30/depreciation_time) -> -655889.09 | M17: =IF(M4>depreciation_time,0,-$C$30/depreciation_time) -> -655889.09 | ... AS17: =IF(AS4>depreciation_time,0,-$C$30/depreciation_time) -> 0
B18: interest (I) | C18: Euro | F18: =IF(F4>term_loan,0,IPMT(Input_Output!$D$57,F4,term_loan,CFpower!$C$35)) -> -472240.14 | G18: =IF(G4>term_loan,0,IPMT(Input_Output!$D$57,G4,term_loan,CFpower!$C$35)) -> -451951.4 | H18: =IF(H4>term_loan,0,IPMT(Input_Output!$D$57,H4,term_loan,CFpower!$C$35)) -> -430445.33 | I18: =IF(I4>term_loan,0,IPMT(Input_Output!$D$57,I4,term_loan,CFpower!$C$35)) -> -407648.9 | J18: =IF(J4>term_loan,0,IPMT(Input_Output!$D$57,J4,term_loan,CFpower!$C$35)) -> -383484.69 | K18: =IF(K4>term_loan,0,IPMT(Input_Output!$D$57,K4,term_loan,CFpower!$C$35)) -> -357870.62 | L18: =IF(L4>term_loan,0,IPMT(Input_Output!$D$57,L4,term_loan,CFpower!$C$35)) -> -330719.7 | M18: =IF(M4>term_loan,0,IPMT(Input_Output!$D$57,M4,term_loan,CFpower!$C$35)) -> -301939.74 | ... AS18: =IF(AS4>term_loan,0,IPMT(Input_Output!$D$57,AS4,term_loan,CFpower!$C$35)) -> 0
B19: payment (J) | C19: Euro | F19: =IF(F4>term_loan,0,PPMT(Input_Output!$D$57,F4,term_loan,$C$35)) -> -338145.7 | G19: =IF(G4>term_loan,0,PPMT(Input_Output!$D$57,G4,term_loan,$C$35)) -> -358434.44 | H19: =IF(H4>term_loan,0,PPMT(Input_Output!$D$57,H4,term_loan,$C$35)) -> -379940.5 | I19: =IF(I4>term_loan,0,PPMT(Input_Output!$D$57,I4,term_loan,$C$35)) -> -402736.93 | J19: =IF(J4>term_loan,0,PPMT(Input_Output!$D$57,J4,term_loan,$C$35)) -> -426901.15 | K19: =IF(K4>term_loan,0,PPMT(Input_Output!$D$57,K4,term_loan,$C$35)) -> -452515.22 | L19: =IF(L4>term_loan,0,PPMT(Input_Output!$D$57,L4,term_loan,$C$35)) -> -479666.13 | M19: =IF(M4>term_loan,0,PPMT(Input_Output!$D$57,M4,term_loan,$C$35)) -> -508446.1 | ... AS19: =IF(AS4>term_loan,0,PPMT(Input_Output!$D$57,AS4,term_loan,$C$35)) -> 0
B20: Total loan charges (K=I+J) | C20: Euro | F20: =SUM(F18,F19) -> -810385.84 | G20: =SUM(G18,G19) -> -810385.84 | H20: =SUM(H18,H19) -> -810385.84 | I20: =SUM(I18,I19) -> -810385.84 | J20: =SUM(J18,J19) -> -810385.84 | K20: =SUM(K18,K19) -> -810385.84 | L20: =SUM(L18,L19) -> -810385.84 | M20: =SUM(M18,M19) -> -810385.84 | ... AS20: =SUM(AS18,AS19) -> 0
B22: Taxable income (L=G+D+I),needs to be recovered from sales | C22: Euro | F22: =F15+F17+F18 -> -2010079.3 | G22: =G15+G17+G18 -> -1989790.6 | H22: =H15+H17+H18 -> -1968284.5 | I22: =I15+I17+I18 -> -1945488.1 | J22: =J15+J17+J18 -> -2221323.9 | K22: =K15+K17+K18 -> -1895709.8 | L22: =L15+L17+L18 -> -1868558.9 | M22: =M15+M17+M18 -> -1839778.9 | ... AS22: =AS15+AS17+AS18 -> 0
B23: Tax (M) | C23: Euro | F23: =-tax*F22 -> 502519.83 | G23: =-tax*G22 -> 497447.64 | H23: =-tax*H22 -> 492071.13 | I23: =-tax*I22 -> 486372.02 | J23: =-tax*J22 -> 555330.97 | K23: =-tax*K22 -> 473927.45 | L23: =-tax*L22 -> 467139.72 | M23: =-tax*M22 -> 459944.73 | ... AS23: =-tax*AS22 -> 0
B25: Net revenue after taxes (N=G+K+M) | C25: Euro | F25: =F15+F20+F23 -> -1189816.1 | G25: =G15+G20+G23 -> -1194888.3 | H25: =H15+H20+H23 -> -1200264.8 | I25: =I15+I20+I23 -> -1205963.9 | J25: =J15+J20+J23 -> -1437005 | K25: =K15+K20+K23 -> -1218408.5 | L25: =L15+L20+L23 -> -1225196.2 | M25: =M15+M20+M23 -> -1232391.2 | ... AS25: =AS15+AS20+AS23 -> 0
B27: Discounted revenue | C27: euro | D27: =NPV(Input_Output!$D$58,F25:AS25) -> -7320761.2
B28: Discounted energy sales | C28: GJ | D28: =NPV(Input_Output!$D$58,F28:AS28) -> 1935177.3 | F28: =(1-tax)*F8 -> 330948.32 | G28: =(1-tax)*G8 -> 330948.32 | H28: =(1-tax)*H8 -> 330948.32 | I28: =(1-tax)*I8 -> 330948.32 | J28: =(1-tax)*J8 -> 330948.32 | K28: =(1-tax)*K8 -> 330948.32 | L28: =(1-tax)*L8 -> 330948.32 | M28: =(1-tax)*M8 -> 330948.32 | ... AS28: =(1-tax)*AS8 -> 0
B30: Total investment | C30: =(capex_subsurface+capex_power+heat_capex)*1000000 -> 9838336.3 | D30: Euro
B31: Project rate | C31: =(1-tax)*loan_rate*debt_share+equity_share*equity_return -> 0.066
B32: capex for fiscal stimulus | C32: =C30 -> 9838336.3 | D32: Euro
B33: fiscal lowering of Earnings before tax (EBT) | C33: =IF(fiscal_stimulus="yes",IF(stimulus_perc*C32>stimulus_max*1000000,stimulus_max*1000000,stimulus_perc*C32),0) -> 0 | D33: Euro
B34: NPV benefit to project | C34: =(C33*tax)/(1+CFpower!C31) -> 0 | D34: Euro
B35: Loan share | C35: =C30*debt_share-C34 -> 7870669 | D35: Euro
B36: Equity share | C36: =equity_share*C30 -> 1967667.3 | D36: Euro
